jmespath/__init__.py
jmespath/ast.py
jmespath/compat.py
jmespath/exceptions.py
jmespath/functions.py
jmespath/lexer.py
jmespath/parser.py
jmespath/scope.py
jmespath/visitor.py
jmespath_community-1.1.3.data/scripts/jp.py
tests/legacy/__init__.py
tests/legacy/test_lexer.py
jmespath_community-1.1.3.dist-info/LICENSE
jmespath_community-1.1.3.dist-info/METADATA
jmespath_community-1.1.3.dist-info/WHEEL
jmespath_community-1.1.3.dist-info/top_level.txt
jmespath_community-1.1.3.dist-info/RECORD
